vector2.py
kvector2-1.4.1.dist-info/LICENSE
kvector2-1.4.1.dist-info/METADATA
kvector2-1.4.1.dist-info/WHEEL
kvector2-1.4.1.dist-info/entry_points.txt
kvector2-1.4.1.dist-info/top_level.txt
kvector2-1.4.1.dist-info/RECORD
