Metadata-Version: 2.1
Name: kvector2
Version: 1.4.1
Summary: implement 2D vectors
Home-page: https://github.com/k39dev/vector2
Author: K 39
License: mit
Platform: UNKNOWN
Requires-Python: >=3.6
